cairo/__init__.py
cairo/__init__.pyi
cairo/_cairo.cp312-win_arm64.pyd
cairo/py.typed
cairo/include/py3cairo.h
pycairo-1.26.0.dist-info/COPYING
pycairo-1.26.0.dist-info/COPYING-LGPL-2.1
pycairo-1.26.0.dist-info/COPYING-MPL-1.1
pycairo-1.26.0.dist-info/METADATA
pycairo-1.26.0.dist-info/WHEEL
pycairo-1.26.0.dist-info/top_level.txt
pycairo-1.26.0.dist-info/RECORD
