Metadata-Version: 2.1
Name: pycairo
Version: 1.26.0
Summary: Python interface for cairo
Home-page: https://pycairo.readthedocs.io
Maintainer: Christoph Reiter
Maintainer-email: reiter.christoph@gmail.com
License: LGPL-2.1-only OR MPL-1.1
Project-URL: Source, https://github.com/pygobject/pycairo
Classifier: Operating System :: OS Independent
Classifier: Programming Language :: Python :: 3
Classifier: Programming Language :: Python :: Implementation :: CPython
Classifier: Programming Language :: Python :: Implementation :: PyPy
Classifier: License :: OSI Approved :: GNU Lesser General Public License v2 (LGPLv2)
Classifier: License :: OSI Approved :: Mozilla Public License 1.1 (MPL 1.1)
Requires-Python: >=3.8
License-File: COPYING
License-File: COPYING-LGPL-2.1
License-File: COPYING-MPL-1.1
